max_random_baseline/__init__.py
max_random_baseline/max_random_baseline.py
max_random_baseline/poibin/__init__.py
max_random_baseline/poibin/poibin.py
max_random_baseline-0.1.1.dist-info/LICENSE
max_random_baseline-0.1.1.dist-info/METADATA
max_random_baseline-0.1.1.dist-info/WHEEL
max_random_baseline-0.1.1.dist-info/top_level.txt
max_random_baseline-0.1.1.dist-info/RECORD
