Metadata-Version: 2.1
Name: max-random-baseline
Version: 0.1.1
Summary: A simple random baseline that accounts for evaluation set size and reuse
Home-page: https://github.com/gyauney/max-random-baseline
Author: Gregory Yauney
Author-email: gyauney@cs.cornell.edu
Classifier: Programming Language :: Python :: 3
Classifier: License :: OSI Approved :: MIT License
Classifier: Operating System :: OS Independent
Requires-Python: >=3.8
License-File: LICENSE
Requires-Dist: numpy
